{
    "$schema": "https://schema.management.azure.com/schemas/2015-01-01/deploymentTemplate.json#",
    "contentVersion": "1.0.0.1",
    "parameters": {
      "moduleAddSubnetsToExistingVNets": {
        "type": "object"
      },
      
      "customTages": {
        "type": "object"
      },
      "suffixes" : {
        "type": "object"
      }
    },
    "variables": {
        "defaultLocation": "[resourceGroup().location]"
    },
    "resources": [
        {
            "copy" : {
                "name": "vNets",
                "count": "[length(parameters('moduleAddSubnetsToExistingVNets').vNets)]"
            },
            "name": "AddSubnets",
            "apiVersion": "2018-03-01",
            "type": "Microsoft.Network/virtualNetworks/subnets",
            "location": "[resourceGroup().location]",
            "properties": {
                "copy" : [
                    {
                        "name": "vNets/subnets",
                        "count": "[length(parameters('moduleAddSubnetsToExistingVNets').vNets[copyIndex('vNets/subnets')].subnets)]",
                        "input" : { 
                            "addressPrefix": "[parameters('moduleAddSubnetsToExistingVNets').vNets[copyIndex('vNets')].subnets[copyIndex('vNets/subnets')].addressPrefix]",
                            "networkSecurityGroup": {
                                "id": "[resourceId('Microsoft.Network/networkSecurityGroups',concat(parameters('moduleAddSubnetsToExistingVNets').vNets[copyIndex('vNets')].subnets[copyIndex('vNets/subnets')].nsgName,parameters('suffixes').nsgSuffix))]"              
                            }
                        }
                   }
                ]
            }
        }
    ],
    "outputs": {
    }
}