{
    "$schema": "https://schema.management.azure.com/schemas/2015-01-01/deploymentTemplate.json#",
    "contentVersion": "1.0.0.1",
    "parameters": {
        "moduleCreateNewADForestandDomain": {
            "type": "object"
        },
        "customTages": {
            "type": "object"
        },
        "suffixes" : {
            "type": "object"
        }
    },
    "variables": {
        "defaultLocation": "[resourceGroup().location]"
    },
    "resources": [
        {
            "type": "extensions",
            "apiVersion": "2019-03-01",
            "name": "CreateADForest",
            "location": "[if(equals(parameters('moduleCreateNewADForestandDomain').location, json('null')), variables('defaultLocation'), parameters('moduleCreateNewADForestandDomain').location)]",
            "dependsOn": [
            ],
            "properties": {
                "publisher": "Microsoft.Powershell",
                "type": "DSC",
                "typeHandlerVersion": "2.19",
                "autoUpgradeMinorVersion": true,
                "settings": {
                    "ModulesUrl": "[uri(parameters('_artifactsLocation'), concat('/CreateADPDC.zip', parameters('_artifactsLocationSasToken')))]",
                    "ConfigurationFunction": "CreateADPDC.ps1\\CreateADPDC",
                    "Properties": {
                        "DomainName": "[parameters('moduleCreateNewADForestandDomain').domainName]",
                        "AdminCreds": {
                            "UserName": "[parameters('moduleCreateNewADForestandDomain').adminUsername]",
                            "Password": "[parameters('moduleCreateNewADForestandDomain').adminPassword]"
                        }
                    }
                }
            }
        }
    ],
    [
{
    "type": "Microsoft.Resources/deployments",
    "apiVersion": "2018-11-01",
    "name": "UpdateVNetDNS",
    "dependsOn": [
        "CreateADForest"
    ],
    "properties": {
        "mode": "Incremental",
        "templateLink": {
            "uri": "[uri(parameters('_artifactsLocation'), concat('nestedtemplates/vnet-with-dns-server.json', parameters('_artifactsLocationSasToken')))]",
            "contentVersion": "1.0.0.0"
        },
        "parameters": {
            "virtualNetworkName": {
                "value": "[variables('virtualNetworkName')]"
            },
            "virtualNetworkAddressRange": {
                "value": "[variables('virtualNetworkAddressRange')]"
            },
            "subnetName": {
                "value": "[variables('adSubnetName')]"
            },
            "subnetRange": {
                "value": "[variables('adSubnetAddressPrefix')]"
            },
            "DNSServerAddress": {
                "value": [
                    "[variables('adNicIPAddress')]"
                ]
            },
            "location": {
                "value": "[parameters('location')]"
            }
        }
    }
}
]
  }
